sailMate/__init__.py
sailMate/sailMate.py
sailmate-0.0.6.dist-info/licenses/LICENSE
sailmate-0.0.6.dist-info/METADATA
sailmate-0.0.6.dist-info/WHEEL
sailmate-0.0.6.dist-info/top_level.txt
sailmate-0.0.6.dist-info/RECORD
