Metadata-Version: 2.4
Name: sailMate
Version: 0.0.6
Summary: A really bad chess engine that served as a learning project
Author-email: Marina M <marinamolina7877@gmail.com>
License-Expression: MIT
Project-URL: Homepage, https://github.com/marinamolinat/Sailmate-a-chess-engine
Classifier: Programming Language :: Python :: 3
Classifier: Operating System :: OS Independent
Requires-Python: >=3.13
License-File: LICENSE
Dynamic: license-file
